{
    "code": 0,
    "msg": null,
    "data": [{
        "id": 1,
        "index": 1,
        "expireTime": 1477827824324,
        "noticeTime": 1477928434339,
        "createTime": 1477928434331,
        "content": "今日需要与学员李四的家长进行沟通，解决李四学习态度的问题",
        "status": 1,
        "userName": "李四"
    }, {
        "id": 1,
        "index": 1,
        "expireTime": 1477827824324,
        "noticeTime": 1477928434339,
        "createTime": 1477928434331,
        "content": "今日需要与学员李四的家长进行沟通，解决李四学习态度的问题",
        "status": 1,
        "userName": "李四"
    }, {
        "id": 1,
        "index": 1,
        "expireTime": 1477827824324,
        "noticeTime": 1477928434339,
        "createTime": 1477928434331,
        "content": "今日需要与学员李四的家长进行沟通，解决李四学习态度的问题",
        "status": 1,
        "userName": "李四"
    }, {
        "id": 1,
        "index": 1,
        "expireTime": 1477827824324,
        "noticeTime": 1477928434339,
        "createTime": 1477928434331,
        "content": "今日需要与学员李四的家长进行沟通，解决李四学习态度的问题",
        "status": 1,
        "userName": "李四"
    }, {
        "id": 1,
        "index": 1,
        "expireTime": 1477827824324,
        "noticeTime": 1477928434339,
        "createTime": 1477928434331,
        "content": "今日需要与学员李四的家长进行沟通，解决李四学习态度的问题",
        "status": 1,
        "userName": "李四"
    }, {
        "id": 1,
        "index": 1,
        "expireTime": 1477827824324,
        "noticeTime": 1477928434339,
        "createTime": 1477928434331,
        "content": "今日需要与学员李四的家长进行沟通，解决李四学习态度的问题",
        "status": 1,
        "userName": "李四"
    }]
}